setup.py
slander/__init__.py
slander/bot.py
slander/conf.py
slander/lang.py
slander.egg-info/PKG-INFO
slander.egg-info/SOURCES.txt
slander.egg-info/dependency_links.txt
slander.egg-info/entry_points.txt
slander.egg-info/not-zip-safe
slander.egg-info/requires.txt
slander.egg-info/top_level.txt