Metadata-Version: 1.1
Name: slander
Version: 0.3
Summary: SLack Agile Not Dangerously Evil Robot
Home-page: https://github.com/cniemira/slander
Author: CJ Niemira
Author-email: siege@siege.org
License: UNKNOWN
Keywords: agile chat slack standup
Platform: UNKNOWN
Classifier: Programming Language :: Python
